filterzyme/__init__.py
filterzyme/pipeline.py
filterzyme/pipeline_v2.py
filterzyme/steps/PLACER_forChai_step.py
filterzyme/steps/PLACER_forVina_step.py
filterzyme/steps/PLACER_step.py
filterzyme/steps/__init__.py
filterzyme/steps/cleanPDB_step.py
filterzyme/steps/computeligandRMSD_step.py
filterzyme/steps/computeproteinRMSD_step.py
filterzyme/steps/dock_vina_step.py
filterzyme/steps/extract_docking_metrics_step.py
filterzyme/steps/fpocket_step.py
filterzyme/steps/geometric_filtering_cofactor.py
filterzyme/steps/geometric_filtering_cofactor_MCS.py
filterzyme/steps/geometric_filtering_esterase.py
filterzyme/steps/ligandSASA_step.py
filterzyme/steps/plip_step.py
filterzyme/steps/predict_catalyticsite_run.py
filterzyme/steps/predict_catalyticsite_step.py
filterzyme/steps/prepareboltz_step.py
filterzyme/steps/preparechai_step.py
filterzyme/steps/preparevina_step.py
filterzyme/steps/save_step.py
filterzyme/steps/step.py
filterzyme/steps/superimposestructures_step.py
filterzyme/utils/__init__.py
filterzyme/utils/helpers.py
filterzyme-0.0.6.data/data/LICENSE
filterzyme-0.0.6.dist-info/licenses/LICENSE
filterzyme-0.0.6.dist-info/METADATA
filterzyme-0.0.6.dist-info/WHEEL
filterzyme-0.0.6.dist-info/entry_points.txt
filterzyme-0.0.6.dist-info/top_level.txt
filterzyme-0.0.6.dist-info/RECORD
