Metadata-Version: 2.4
Name: filterzyme
Version: 0.0.6
Home-page: https://github.com/HelenSchmid/Filterzyme
Author: Helen Schmid
Author-email: schmid.helen2@gmail.com
License: GPL3
Project-URL: Bug Tracker, https://github.com/HelenSchmid/Filterzyme/issues
Project-URL: Documentation, https://github.com/HelenSchmid/Filterzyme
Project-URL: Source Code, https://github.com/HelenSchmid/Filterzyme
Keywords: util
Classifier: Development Status :: 5 - Production/Stable
Classifier: Intended Audience :: Science/Research
Classifier: License :: OSI Approved :: GNU General Public License v3 (GPLv3)
Classifier: Natural Language :: English
Classifier: Operating System :: OS Independent
Classifier: Programming Language :: Python :: 3.6
Classifier: Programming Language :: Python :: 3.7
Classifier: Programming Language :: Python :: 3.8
Classifier: Topic :: Scientific/Engineering :: Bio-Informatics
License-File: LICENSE
Requires-Dist: pandas
Requires-Dist: numpy
Requires-Dist: tqdm
Requires-Dist: biopython
Requires-Dist: biotite
Requires-Dist: matplotlib
Requires-Dist: seaborn
Requires-Dist: rdkit
Requires-Dist: freesasa
Requires-Dist: plip
Requires-Dist: enzymetk
Requires-Dist: docko
Dynamic: author
Dynamic: author-email
Dynamic: classifier
Dynamic: description
Dynamic: description-content-type
Dynamic: home-page
Dynamic: keywords
Dynamic: license
Dynamic: license-file
Dynamic: project-url
Dynamic: requires-dist
